{
  "backlog_surface_class": "generated-mapping-bridge-backlog",
  "canonical_requirement_artifact": "requirements/2010/canonical_requirements.json",
  "canonical_requirement_row_count": 880,
  "canonical_requirement_status_counts": {
    "pass": 880
  },
  "families": [
    {
      "description": "Clause 4 decomposition backlog for federation lifecycle and synchronization services.",
      "family": "Federation Management",
      "kinds": {},
      "open_row_count": 0,
      "queue_item_count": 0,
      "queue_items": [],
      "statuses": {}
    },
    {
      "description": "Clause 5 packet-to-curated backlog for declaration services.",
      "family": "Declaration Management",
      "kinds": {},
      "open_row_count": 0,
      "queue_item_count": 0,
      "queue_items": [],
      "statuses": {}
    },
    {
      "description": "Clause 6 packet-to-curated backlog for object-management services.",
      "family": "Object Management",
      "kinds": {},
      "open_row_count": 0,
      "queue_item_count": 0,
      "queue_items": [],
      "statuses": {}
    },
    {
      "description": "Clause 7 packet-to-curated backlog for ownership-management services.",
      "family": "Ownership Management",
      "kinds": {},
      "open_row_count": 0,
      "queue_item_count": 0,
      "queue_items": [],
      "statuses": {}
    },
    {
      "description": "Clause 8 packet-to-curated backlog for time-management services.",
      "family": "Time Management",
      "kinds": {},
      "open_row_count": 0,
      "queue_item_count": 0,
      "queue_items": [],
      "statuses": {}
    },
    {
      "description": "Clause 9 packet-to-curated backlog for DDM services.",
      "family": "Data Distribution Management",
      "kinds": {},
      "open_row_count": 0,
      "queue_item_count": 0,
      "queue_items": [],
      "statuses": {}
    },
    {
      "description": "Clause 10 packet-to-curated backlog for support services.",
      "family": "Support Services",
      "kinds": {},
      "open_row_count": 0,
      "queue_item_count": 0,
      "queue_items": [],
      "statuses": {}
    },
    {
      "description": "Cross-cutting MOM observer, MOM service-reporting, and standard MIM backlog rows.",
      "family": "MOM/MIM",
      "kinds": {},
      "open_row_count": 0,
      "queue_item_count": 0,
      "queue_items": [],
      "statuses": {}
    },
    {
      "description": "Open IEEE 1516.2 OMT parser, merge, and model-structure backlog rows.",
      "family": "OMT",
      "kinds": {},
      "open_row_count": 0,
      "queue_item_count": 0,
      "queue_items": [],
      "statuses": {}
    },
    {
      "description": "Open IEEE 1516.2 XML and schema-conformance backlog rows.",
      "family": "XML",
      "kinds": {},
      "open_row_count": 0,
      "queue_item_count": 0,
      "queue_items": [],
      "statuses": {}
    },
    {
      "description": "Cross-cutting native/gRPC/REST transport-equivalence and transportation-type backlog rows.",
      "family": "Transports",
      "kinds": {},
      "open_row_count": 0,
      "queue_item_count": 0,
      "queue_items": [],
      "statuses": {}
    }
  ],
  "generated_from": "canonical 2010 requirement catalog + mapping-bridge/import-history backlog projection",
  "source_artifact_classes": {
    "requirements/2010/hla1516_1_clause_10_sup_detailed_reconciliation.csv": "mapping-bridge",
    "requirements/2010/hla1516_1_clause_4_fm_service_decomposition.csv": "import-history",
    "requirements/2010/hla1516_1_clause_5_dm_detailed_reconciliation.csv": "mapping-bridge",
    "requirements/2010/hla1516_1_clause_6_om_detailed_reconciliation.csv": "mapping-bridge",
    "requirements/2010/hla1516_1_clause_7_own_detailed_reconciliation.csv": "mapping-bridge",
    "requirements/2010/hla1516_1_clause_8_tm_detailed_reconciliation.csv": "mapping-bridge",
    "requirements/2010/hla1516_1_clause_9_ddm_detailed_reconciliation.csv": "mapping-bridge",
    "requirements/2010/hla1516_2_omt.csv": "import-history"
  },
  "source_artifacts": [
    "requirements/2010/hla1516_1_clause_10_sup_detailed_reconciliation.csv",
    "requirements/2010/hla1516_1_clause_4_fm_service_decomposition.csv",
    "requirements/2010/hla1516_1_clause_5_dm_detailed_reconciliation.csv",
    "requirements/2010/hla1516_1_clause_6_om_detailed_reconciliation.csv",
    "requirements/2010/hla1516_1_clause_7_own_detailed_reconciliation.csv",
    "requirements/2010/hla1516_1_clause_8_tm_detailed_reconciliation.csv",
    "requirements/2010/hla1516_1_clause_9_ddm_detailed_reconciliation.csv",
    "requirements/2010/hla1516_2_omt.csv"
  ],
  "total_open_rows": 0,
  "total_queue_items": 0
}
